Metadata-Version: 1.0
Name: SuvoTest
Version: 0.1
Summary: This is my first package
Home-page: https://github.com/Suvodeep90/SuvoTest
Author: Suvodeep
Author-email: Suvodeep.Majumder90@gmail.com
License: MIT
Platform: UNKNOWN
